<Properties StartupConfiguration="{B0E5B2E6-9CC7-483A-B626-8BC13B1CE35D}|Default">
  <MonoDevelop.Ide.Workbench ActiveDocument="Controllers/CityController.cs">
    <Files>
      <File FileName="Controllers/CityController.cs" Line="46" Column="14" />
      <File FileName="Models/City.cs" Line="16" Column="2" />
      <File FileName="Properties/launchSettings.json" Line="1" Column="2" />
      <File FileName="appsettings.json" Line="3" Column="10" />
    </Files>
    <Pads>
      <Pad Id="ProjectPad">
        <State name="__root__">
          <Node name="Cityy" expanded="True">
            <Node name="Cityy" expanded="True">
              <Node name="Controllers" expanded="True" />
              <Node name="Models" expanded="True" />
              <Node name="Properties" expanded="True" />
            </Node>
          </Node>
        </State>
      </Pad>
      <Pad Id="MonoDevelop.Debugger.WatchPad">
        <State />
      </Pad>
    </Pads>
  </MonoDevelop.Ide.Workbench>
  <MonoDevelop.Ide.ItemProperties.Cityy PreferredExecutionTarget="/Applications/Microsoft Edge.app" />
  <MonoDevelop.Ide.DebuggingService.PinnedWatches />
  <MonoDevelop.Ide.Workspace ActiveConfiguration="Debug" />
  <MultiItemStartupConfigurations />
  <MonoDevelop.Ide.DebuggingService.Breakpoints>
    <BreakpointStore />
  </MonoDevelop.Ide.DebuggingService.Breakpoints>
</Properties>